{
    "commands": [
        {
            "text": "karma",
            "aliases": ["karma", "rep", "reputation"],
            "description": "Shows the amount of karma you have.",
            "usage": "?karma",
            "sub": [
                {
                    "text": "leaderboard",
                    "aliases": ["leaderboard", "lb", "top"],
                    "description": "Shows the karma leaderboard of the server.",
                    "usage": "?karma leaderboard"
                }
            ],
            "options": [
                {
                    "type": 6,
                    "name": "user",
                    "description": "A user."
                }
            ],
            "show": true,
            "slash": true
        },
        {
            "text": "balance",
            "aliases": ["bal", "money"],
            "description": "Shows the amount of money you have.",
            "usage": "?balance",
            "show": true,
            "slash": true
        },
        {
            "text": "trivia",
            "aliases": ["question", "q", "t"],
            "description": "Gives you a random trivia question.",
            "usage": "?trivia",
            "show": true,
            "slash": true
        },
        {
            "text": "say",
            "aliases": ["say, repeat"],
            "description": "Deletes your message and repeats it, making it look like the bot said it.",
            "usage": "?say",
            "show": false,
            "slash": false
        },
        {
            "text": "help",
            "aliases": ["help", "welp"],
            "description": "An embed with all the commands.",
            "usage": "?help",
            "show": true,
            "slash": true
        },
        {
            "text": "shop",
            "aliases": ["shop", "store"],
            "description": "An embed with all the items in the shop.",
            "usage": "?shop",
            "show": true,
            "slash": true
        },
        {
            "text": "buy",
            "aliases": ["buy", "purchase"],
            "description": "Buy an item from the store.",
            "usage": "?buy (item)",
            "show": true,
            "slash": true
        },
        {
            "text": "sell",
            "aliases": ["sell"],
            "description": "Sell an item for half the price.",
            "usage": "?sell (item)",
            "show": true,
            "slash": true
        },
        {
            "text": "inventory",
            "aliases": ["inventory", "inv"],
            "description": "Shows your inventory.",
            "usage": "?inventory",
            "show": true,
            "slash": true
        }
    ]
}
